dudendas/__init__.py
dudendas/__main__.py
dudendas/arguments.py
dudendas/dudendas.py
dudendas/exception.py
dudendas/logging.py
dudendas/network.py
dudendas/search.py
dudendas/util.py
dudendas/version.py
dudendas/word.py
dudendas-1.0.3.dist-info/LICENSE
dudendas-1.0.3.dist-info/METADATA
dudendas-1.0.3.dist-info/WHEEL
dudendas-1.0.3.dist-info/entry_points.txt
dudendas-1.0.3.dist-info/top_level.txt
dudendas-1.0.3.dist-info/RECORD
