Metadata-Version: 2.1
Name: dudendas
Version: 1.0.3
Summary: A tool for collecting words from Duden.
Home-page: https://pypi.python.org/pypi/dudendas
Author: eikendev
Author-email: raphael@eiken.dev
License: MIT
Keywords: duden
Platform: UNKNOWN
Classifier: Development Status :: 4 - Beta
Classifier: Intended Audience :: Developers
Classifier: License :: OSI Approved :: MIT License
Classifier: Programming Language :: Python :: 3
Classifier: Topic :: Utilities
Classifier: Environment :: Console
Classifier: Operating System :: POSIX
Requires-Python: >=3
Requires-Dist: requests ; python_version >= "2.0.0"
Requires-Dist: aiohttp ; python_version >= "3.0.0"
